Workbook

Sheet Cover
B2: Acrowell AI Assistant — Cost & Pricing Model
B4: Editable cost model: Gemini-only vs Hybrid (Qwen3-30B text + Gemma-4-26B vision). Change inputs on the Inputs sheet — everything recalculates.
B6: Key results (at default inputs)
B7: All-Gemini cost / user / month | C7: ='Cost Model'!C14
B8: Hybrid cost / user / month | C8: ='Cost Model'!D14
B9: 50-rep company / month (Hybrid) | C9: ='Cost Model'!D16
B10: Monthly savings vs Gemini (50 reps) | C10: ='Cost Model'!E18
B11: Margin at list price (Hybrid) | C11: ='Cost Model'!D21
B14: Sheet index
B15: Inputs | C15: All editable assumptions (blue cells) — usage, tokens, model rates, pricing
B16: Cost Model | C16: Per-message → per-user → per-company costs, margins, free-tier offset
B17: Scale | C17: Cost / revenue / profit from 10 to 500 reps + 12-month projection
B18: Sources | C18: Pricing data sources (July 2026)
B21: Blue = input you can edit · Black = formula · Green = cross-sheet reference · Red = external data

Sheet Inputs
B2: Inputs & Assumptions (edit blue cells)
B4: Usage
B5: Messages per user per day | C5: 400
B6: Share of messages that are bill PDFs | C6: 0.5 | D6: order extraction via photo/PDF
B7: Reps (users) | C7: 50
B8: Billing days per month | C8: 30
B10: Token profile per message
B11: Cached prefix tokens (system prompt + 31 tools) | C11: 2360
B12: Fresh input tokens — text message | C12: 150 | D12: user msg + history + vocab
B13: Output tokens — text intent JSON | C13: 80
B14: Image tokens per bill PDF page | C14: 1000 | D14: after 1024px downscale
B15: Output tokens — PDF order JSON | C15: 400
B17: Model rates ($ per 1M tokens)
B18: Model | C18: Input $/M | D18: Cached in $/M | E18: Output $/M
B19: Gemini 3.1 Flash-Lite | C19: 0.25 | D19: 0.025 | E19: 1.5
B20: Qwen3-30B-A3B (Workers AI) | C20: 0.051 | D20: — | E20: 0.335
B21: Gemma-4-26B (Workers AI, vision) | C21: 0.1 | D21: — | E21: 0.3
B23: Cloudflare free tier
B24: Free neurons per day | C24: 14000
B25: Qwen neurons per text msg | C25: 14 | D25: 4625/M in + 30475/M out
B26: Gemma neurons per PDF msg | C26: 43 | D26: 9091/M in + 27273/M out
B28: Pricing & FX
B29: List price per user per month (₹) | C29: 999
B30: INR per USD | C30: 90

Sheet Cost Model
B2: Cost Model — Gemini-only vs Hybrid
B4: Metric | C4: All-Gemini | D4: Hybrid (Qwen+Gemma) | E4: Notes
B5: Cost per text message (₹) | C5: =(Inputs!C11*Inputs!D19+Inputs!C12*Inputs!C19+Inputs!C13*Inputs!E19)/1000000*Inputs!C30 | D5: =((Inputs!C11+Inputs!C12)*Inputs!C20+Inputs!C13*Inputs!E20)/1000000*Inputs!C30 | E5: cached prefix at 10% rate on Gemini
B6: Cost per PDF order message (₹) | C6: =(Inputs!C11*Inputs!D19+(Inputs!C12+Inputs!C14)*Inputs!C19+Inputs!C15*Inputs!E19)/1000000*Inputs!C30 | D6: =((Inputs!C11+Inputs!C12+Inputs!C14)*Inputs!C21+Inputs!C15*Inputs!E21)/1000000*Inputs!C30 | E6: image tokens never cached
B8: Per user per day (₹)
B9: Text messages (₹) | C9: =C5*Inputs!C5*(1-Inputs!C6) | D9: =D5*Inputs!C5*(1-Inputs!C6)
B10: PDF messages (₹) | C10: =C6*Inputs!C5*Inputs!C6 | D10: =D6*Inputs!C5*Inputs!C6
B11: Free-tier offset (₹) | C11: 0 | D11: =-MIN(1,Inputs!C24/(Inputs!C7*(Inputs!C5*(1-Inputs!C6)*Inputs!C25+Inputs!C5*Inputs!C6*Inputs!C26)))*(D9+D10) | E11: free neurons cover this share of daily use
B12: Total per user per day (₹) | C12: =C9+C10+C11 | D12: =D9+D10+D11
B14: Per user per month (₹) | C14: =C12*Inputs!C8 | D14: =D12*Inputs!C8
B16: Company per month (₹) | C16: =C14*Inputs!C7 | D16: =D14*Inputs!C7
B18: Savings vs Gemini / month (₹) | E18: =C16-D16
B19: Savings % | E19: =E18/C16
B21: Margin at list price (Hybrid) | D21: =(Inputs!C29-D14)/Inputs!C29
B22: Profit per company / month (₹) | C22: =(Inputs!C29-C14)*Inputs!C7 | D22: =(Inputs!C29-D14)*Inputs!C7

Sheet Scale
B2: Scale — monthly cost, revenue, profit by company size
B4: Reps | C4: Gemini cost ₹/mo | D4: Hybrid cost ₹/mo | E4: Revenue ₹/mo | F4: Profit (Hybrid) ₹/mo | G4: Margin %
B5: 10 | C5: ='Cost Model'!C14*B5 | D5: ='Cost Model'!D14*B5 | E5: =Inputs!C29*B5 | F5: =E5-D5 | G5: =F5/E5
B6: 25 | C6: ='Cost Model'!C14*B6 | D6: ='Cost Model'!D14*B6 | E6: =Inputs!C29*B6 | F6: =E6-D6 | G6: =F6/E6
B7: 50 | C7: ='Cost Model'!C14*B7 | D7: ='Cost Model'!D14*B7 | E7: =Inputs!C29*B7 | F7: =E7-D7 | G7: =F7/E7
B8: 100 | C8: ='Cost Model'!C14*B8 | D8: ='Cost Model'!D14*B8 | E8: =Inputs!C29*B8 | F8: =E8-D8 | G8: =F8/E8
B9: 250 | C9: ='Cost Model'!C14*B9 | D9: ='Cost Model'!D14*B9 | E9: =Inputs!C29*B9 | F9: =E9-D9 | G9: =F9/E9
B10: 500 | C10: ='Cost Model'!C14*B10 | D10: ='Cost Model'!D14*B10 | E10: =Inputs!C29*B10 | F10: =E10-D10 | G10: =F10/E10
B32: 12-month projection (Hybrid, starting reps, +15% growth/mo)
B33: Month | C33: Reps | D33: Cost ₹ | E33: Revenue ₹ | F33: Profit ₹
B34: 1 | C34: =Inputs!C7 | D34: ='Cost Model'!D14*C34 | E34: =Inputs!C29*C34 | F34: =E34-D34
B35: 2 | C35: =ROUND(C34*1.15,0) | D35: ='Cost Model'!D14*C35 | E35: =Inputs!C29*C35 | F35: =E35-D35
B36: 3 | C36: =ROUND(C35*1.15,0) | D36: ='Cost Model'!D14*C36 | E36: =Inputs!C29*C36 | F36: =E36-D36
B37: 4 | C37: =ROUND(C36*1.15,0) | D37: ='Cost Model'!D14*C37 | E37: =Inputs!C29*C37 | F37: =E37-D37
B38: 5 | C38: =ROUND(C37*1.15,0) | D38: ='Cost Model'!D14*C38 | E38: =Inputs!C29*C38 | F38: =E38-D38
B39: 6 | C39: =ROUND(C38*1.15,0) | D39: ='Cost Model'!D14*C39 | E39: =Inputs!C29*C39 | F39: =E39-D39
B40: 7 | C40: =ROUND(C39*1.15,0) | D40: ='Cost Model'!D14*C40 | E40: =Inputs!C29*C40 | F40: =E40-D40
B41: 8 | C41: =ROUND(C40*1.15,0) | D41: ='Cost Model'!D14*C41 | E41: =Inputs!C29*C41 | F41: =E41-D41
B42: 9 | C42: =ROUND(C41*1.15,0) | D42: ='Cost Model'!D14*C42 | E42: =Inputs!C29*C42 | F42: =E42-D42
B43: 10 | C43: =ROUND(C42*1.15,0) | D43: ='Cost Model'!D14*C43 | E43: =Inputs!C29*C43 | F43: =E43-D43
B44: 11 | C44: =ROUND(C43*1.15,0) | D44: ='Cost Model'!D14*C44 | E44: =Inputs!C29*C44 | F44: =E44-D44
B45: 12 | C45: =ROUND(C44*1.15,0) | D45: ='Cost Model'!D14*C45 | E45: =Inputs!C29*C45 | F45: =E45-D45

Sheet Sources
B2: Sources (pricing verified July 2026)
B4: Data | C4: Source Name | D4: Source URL
B5: Gemini 3.1 Flash-Lite $0.25/$1.50 per M, cache ~10% | C5: BenchLM Gemini pricing (synced from Google) | D5: https://benchlm.ai/google/api-pricing
B6: Gemini caching 90% savings + Batch 50% off | C6: CostGoat Gemini guide | D6: https://costgoat.com/pricing/gemini-api
B7: Qwen3-30B / Gemma-4-26B / neuron rates | C7: Cloudflare Workers AI pricing docs | D7: https://developers.cloudflare.com/workers-ai/platform/pricing/
B8: Free neuron allocation (~10K/day) | C8: Cloudflare Workers AI docs | D8: https://developers.cloudflare.com/workers-ai/platform/pricing/
B9: LLM market pricing context | C9: Opslyft LLM pricing 2026 | D9: https://www.opslyft.com/blog/llm-pricing-comparison-cost-per-token
B11: Note: re-verify rates on official pages before contract decisions; third-party trackers were used.
